CHANGELOG.txt
LICENCE.txt
MANIFEST.in
README.txt
setup.py
aashikacalc/__init__.py
aashikacalc/simple_calculator.py
aashikacalc.egg-info/PKG-INFO
aashikacalc.egg-info/SOURCES.txt
aashikacalc.egg-info/dependency_links.txt
aashikacalc.egg-info/top_level.txt