Metadata-Version: 2.1
Name: aashikacalc
Version: 0.0.1
Summary: A very simple Calculator
Home-page: 
Author: Aashika M
Author-email: aashika98187@gmail.com
License: MIT
Keywords: calculator
Classifier: Development Status :: 5 - Production/Stable
Classifier: Intended Audience :: Education
Classifier: Operating System :: Microsoft :: Windows :: Windows 10
Classifier: License :: OSI Approved :: MIT License
Classifier: Programming Language :: Python :: 3
License-File: LICENCE.txt
